LICENSE.txt
MANIFEST.in
README.rst
setup.py
django_auth_iam/__init__.py
django_auth_iam/backends.py
django_auth_iam/models.py
django_auth_iam/properties.py
django_auth_iam/tests.py
django_auth_iam/utils.py
django_auth_iam.egg-info/PKG-INFO
django_auth_iam.egg-info/SOURCES.txt
django_auth_iam.egg-info/dependency_links.txt
django_auth_iam.egg-info/requires.txt
django_auth_iam.egg-info/top_level.txt
docs/api.rst
docs/conf.py
docs/index.rst
docs/settings.rst
docs/setup.rst
docs/usage.rst