Metadata-Version: 1.0
Name: django-auth-iam
Version: 0.1.3
Summary: Django authentication backend using Amazon IAM
Home-page: https://github.com/viewworld/django-auth-iam/
Author: Michael Budde
Author-email: mb@viewworld.dk
License: GPL v3
Keywords: django,amazon,authentication,auth
Platform: UNKNOWN
Classifier: Development Status :: 3 - Alpha
Classifier: Framework :: Django
Classifier: License :: OSI Approved :: GNU General Public License (GPL)
Classifier: Programming Language :: Python
Classifier: Topic :: Security
Classifier: Topic :: System :: Systems Administration :: Authentication/Directory
